{"config": {"view": {"continuousWidth": 300, "continuousHeight": 300}}, "hconcat": [{"mark": {"type": "rect"}, "encoding": {"color": {"field": "COUNT", "scale": {"scheme": "blues"}, "title": "Number of Licenses", "type": "quantitative"}, "tooltip": [{"field": "License Type", "type": "nominal"}, {"field": "Zip", "type": "nominal"}, {"field": "COUNT", "type": "quantitative"}], "x": {"field": "Zip", "sort": "-y", "title": "Zip Code", "type": "nominal"}, "y": {"field": "License Type", "sort": "-x", "title": "License Type", "type": "nominal"}}, "height": 450, "name": "view_13", "title": "License Type \u00d7 Zip Code (Top 40 Zips) \u2013 Drag to Select", "width": 375}, {"mark": {"type": "bar", "color": "#4C72B0"}, "encoding": {"tooltip": [{"field": "Zip", "type": "nominal"}, {"field": "COUNT", "type": "quantitative"}], "x": {"field": "COUNT", "title": "Licenses in Selected Area", "type": "quantitative"}, "y": {"field": "Zip", "sort": "-x", "title": "Zip Code", "type": "nominal"}}, "height": 450, "title": "Licenses for Selected Area", "transform": [{"filter": {"param": "param_14"}}], "width": 230}], "data": {"name": "data-f4a7fb43ec7e8cd6d849da6815d54b33"}, "params": [{"name": "param_14", "select": {"type": "interval", "encodings": ["x", "y"]}, "views": ["view_13"]}], "$schema": "https://vega.github.io/schema/vega-lite/v5.20.1.json", "datasets": {"data-f4a7fb43ec7e8cd6d849da6815d54b33": [{"License Type": "ATHLETICS", "Zip": "60623", "COUNT": 1}, {"License Type": "CLIN PSYCHOLOGIST", "Zip": "60612", "COUNT": 1}, {"License Type": "COMM ASSOC MGR", "Zip": "60634", "COUNT": 1}, {"License Type": "COSMO", "Zip": "60406.0", "COUNT": 3}, {"License Type": "COSMO", "Zip": "60426.0", "COUNT": 7}, {"License Type": "COSMO", "Zip": "60453", "COUNT": 15}, {"License Type": "COSMO", "Zip": "60453.0", "COUNT": 14}, {"License Type": "COSMO", "Zip": "60608.0", "COUNT": 8}, {"License Type": "COSMO", "Zip": "60609.0", "COUNT": 7}, {"License Type": "COSMO", "Zip": "60612", "COUNT": 4}, {"License Type": "COSMO", "Zip": "60612.0", "COUNT": 8}, {"License Type": "COSMO", "Zip": "60616", "COUNT": 11}, {"License Type": "COSMO", "Zip": "60616.0", "COUNT": 8}, {"License Type": "COSMO", "Zip": "60617", "COUNT": 12}, {"License Type": "COSMO", "Zip": "60617.0", "COUNT": 17}, {"License Type": "COSMO", "Zip": "60619", "COUNT": 11}, {"License Type": "COSMO", "Zip": "60619.0", "COUNT": 22}, {"License Type": "COSMO", "Zip": "60620", "COUNT": 6}, {"License Type": "COSMO", "Zip": "60620.0", "COUNT": 12}, {"License Type": "COSMO", "Zip": "60621.0", "COUNT": 4}, {"License Type": "COSMO", "Zip": "60623", "COUNT": 6}, {"License Type": "COSMO", "Zip": "60623.0", "COUNT": 6}, {"License Type": "COSMO", "Zip": "60624.0", "COUNT": 7}, {"License Type": "COSMO", "Zip": "60625.0", "COUNT": 17}, {"License Type": "COSMO", "Zip": "60628", "COUNT": 10}, {"License Type": "COSMO", "Zip": "60628.0", "COUNT": 23}, {"License Type": "COSMO", "Zip": "60629.0", "COUNT": 7}, {"License Type": "COSMO", "Zip": "60631.0", "COUNT": 10}, {"License Type": "COSMO", "Zip": "60632.0", "COUNT": 14}, {"License Type": "COSMO", "Zip": "60634", "COUNT": 17}, {"License Type": "COSMO", "Zip": "60634.0", "COUNT": 12}, {"License Type": "COSMO", "Zip": "60636.0", "COUNT": 7}, {"License Type": "COSMO", "Zip": "60637.0", "COUNT": 8}, {"License Type": "COSMO", "Zip": "60638.0", "COUNT": 14}, {"License Type": "COSMO", "Zip": "60639.0", "COUNT": 12}, {"License Type": "COSMO", "Zip": "60643.0", "COUNT": 11}, {"License Type": "COSMO", "Zip": "60644.0", "COUNT": 6}, {"License Type": "COSMO", "Zip": "60649", "COUNT": 1}, {"License Type": "COSMO", "Zip": "60649.0", "COUNT": 5}, {"License Type": "COSMO", "Zip": "60651.0", "COUNT": 10}, {"License Type": "COSMO", "Zip": "60652.0", "COUNT": 9}, {"License Type": "COSMO", "Zip": "60653.0", "COUNT": 8}, {"License Type": "COSMO", "Zip": "60827.0", "COUNT": 2}, {"License Type": "DENTAL", "Zip": "60453", "COUNT": 6}, {"License Type": "DENTAL", "Zip": "60612", "COUNT": 24}, {"License Type": "DENTAL", "Zip": "60616", "COUNT": 4}, {"License Type": "DENTAL", "Zip": "60617", "COUNT": 1}, {"License Type": "DENTAL", "Zip": "60619", "COUNT": 2}, {"License Type": "DENTAL", "Zip": "60623", "COUNT": 2}, {"License Type": "DENTAL", "Zip": "60628", "COUNT": 1}, {"License Type": "DENTAL", "Zip": "60634", "COUNT": 6}, {"License Type": "DETECTIVE BOARD", "Zip": "60406.0", "COUNT": 37}, {"License Type": "DETECTIVE BOARD", "Zip": "60426.0", "COUNT": 23}, {"License Type": "DETECTIVE BOARD", "Zip": "60453", "COUNT": 8}, {"License Type": "DETECTIVE BOARD", "Zip": "60453.0", "COUNT": 20}, {"License Type": "DETECTIVE BOARD", "Zip": "60608.0", "COUNT": 22}, {"License Type": "DETECTIVE BOARD", "Zip": "60609.0", "COUNT": 34}, {"License Type": "DETECTIVE BOARD", "Zip": "60612", "COUNT": 14}, {"License Type": "DETECTIVE BOARD", "Zip": "60612.0", "COUNT": 39}, {"License Type": "DETECTIVE BOARD", "Zip": "60616", "COUNT": 15}, {"License Type": "DETECTIVE BOARD", "Zip": "60616.0", "COUNT": 58}, {"License Type": "DETECTIVE BOARD", "Zip": "60617", "COUNT": 19}, {"License Type": "DETECTIVE BOARD", "Zip": "60617.0", "COUNT": 58}, {"License Type": "DETECTIVE BOARD", "Zip": "60619", "COUNT": 25}, {"License Type": "DETECTIVE BOARD", "Zip": "60619.0", "COUNT": 71}, {"License Type": "DETECTIVE BOARD", "Zip": "60620", "COUNT": 32}, {"License Type": "DETECTIVE BOARD", "Zip": "60620.0", "COUNT": 87}, {"License Type": "DETECTIVE BOARD", "Zip": "60621.0", "COUNT": 50}, {"License Type": "DETECTIVE BOARD", "Zip": "60623", "COUNT": 21}, {"License Type": "DETECTIVE BOARD", "Zip": "60623.0", "COUNT": 35}, {"License Type": "DETECTIVE BOARD", "Zip": "60624.0", "COUNT": 33}, {"License Type": "DETECTIVE BOARD", "Zip": "60625.0", "COUNT": 16}, {"License Type": "DETECTIVE BOARD", "Zip": "60628", "COUNT": 29}, {"License Type": "DETECTIVE BOARD", "Zip": "60628.0", "COUNT": 94}, {"License Type": "DETECTIVE BOARD", "Zip": "60629.0", "COUNT": 49}, {"License Type": "DETECTIVE BOARD", "Zip": "60631.0", "COUNT": 35}, {"License Type": "DETECTIVE BOARD", "Zip": "60632.0", "COUNT": 25}, {"License Type": "DETECTIVE BOARD", "Zip": "60634", "COUNT": 6}, {"License Type": "DETECTIVE BOARD", "Zip": "60634.0", "COUNT": 28}, {"License Type": "DETECTIVE BOARD", "Zip": "60636.0", "COUNT": 46}, {"License Type": "DETECTIVE BOARD", "Zip": "60637.0", "COUNT": 35}, {"License Type": "DETECTIVE BOARD", "Zip": "60638.0", "COUNT": 33}, {"License Type": "DETECTIVE BOARD", "Zip": "60639.0", "COUNT": 27}, {"License Type": "DETECTIVE BOARD", "Zip": "60643.0", "COUNT": 49}, {"License Type": "DETECTIVE BOARD", "Zip": "60644.0", "COUNT": 34}, {"License Type": "DETECTIVE BOARD", "Zip": "60649", "COUNT": 33}, {"License Type": "DETECTIVE BOARD", "Zip": "60649.0", "COUNT": 61}, {"License Type": "DETECTIVE BOARD", "Zip": "60651.0", "COUNT": 30}, {"License Type": "DETECTIVE BOARD", "Zip": "60652.0", "COUNT": 32}, {"License Type": "DETECTIVE BOARD", "Zip": "60653.0", "COUNT": 38}, {"License Type": "DETECTIVE BOARD", "Zip": "60827.0", "COUNT": 38}, {"License Type": "DIETETIC AND NUTRITION", "Zip": "60628", "COUNT": 1}, {"License Type": "FUNERAL AND EMBALMER", "Zip": "60453", "COUNT": 1}, {"License Type": "FUNERAL AND EMBALMER", "Zip": "60617", "COUNT": 3}, {"License Type": "FUNERAL AND EMBALMER", "Zip": "60623", "COUNT": 1}, {"License Type": "FUNERAL AND EMBALMER", "Zip": "60634", "COUNT": 1}, {"License Type": "LIMITED LIABILITY CO", "Zip": "60453", "COUNT": 1}, {"License Type": "MASSAGE LICENSING BD", "Zip": "60453", "COUNT": 1}, {"License Type": "MASSAGE LICENSING BD", "Zip": "60623", "COUNT": 1}, {"License Type": "MASSAGE LICENSING BD", "Zip": "60634", "COUNT": 1}]}}